mlschema/__init__.py
mlschema/mls.py
mlschema/py.typed
mlschema/core/__init__.py
mlschema/core/app/__init__.py
mlschema/core/app/registry.py
mlschema/core/app/service.py
mlschema/core/app/strategy.py
mlschema/core/domain/__init__.py
mlschema/core/domain/base_field.py
mlschema/core/exceptions/__init__.py
mlschema/core/exceptions/_base.py
mlschema/core/exceptions/registry.py
mlschema/core/exceptions/service.py
mlschema/core/util/__init__.py
mlschema/core/util/dtypes.py
mlschema/strategies/__init__.py
mlschema/strategies/app/__init__.py
mlschema/strategies/app/boolean_strategy.py
mlschema/strategies/app/category_strategy.py
mlschema/strategies/app/date_strategy.py
mlschema/strategies/app/number_strategy.py
mlschema/strategies/app/text_strategy.py
mlschema/strategies/domain/__init__.py
mlschema/strategies/domain/boolean_field.py
mlschema/strategies/domain/category_field.py
mlschema/strategies/domain/date_field.py
mlschema/strategies/domain/field_types.py
mlschema/strategies/domain/number_field.py
mlschema/strategies/domain/text_field.py
mlschema-0.1.1.dist-info/METADATA
mlschema-0.1.1.dist-info/WHEEL
mlschema-0.1.1.dist-info/licenses/AUTHORS.md
mlschema-0.1.1.dist-info/licenses/LICENSE
mlschema-0.1.1.dist-info/RECORD
