Metadata-Version: 2.4
Name: mlschema
Version: 0.1.1
Summary: Production-ready DataFrame to JSON Schema converter with extensible validation strategies
Project-URL: Homepage, https://github.com/UlloaSP/mlschema
Project-URL: Documentation, https://ulloasp.github.io/mlschema/
Project-URL: Repository, https://github.com/UlloaSP/mlschema
Project-URL: Bug Tracker, https://github.com/UlloaSP/mlschema/issues
Project-URL: Source Code, https://github.com/UlloaSP/mlschema
Project-URL: Changelog, https://github.com/UlloaSP/mlschema/blob/main/CHANGELOG.md
Project-URL: Discussions, https://github.com/UlloaSP/mlschema/discussions
Project-URL: Funding, https://github.com/sponsors/UlloaSP
Project-URL: Release Notes, https://github.com/UlloaSP/mlschema/releases
Author-email: Pablo Ulloa Santín <pablo.ulloa.santin@udc.es>
Maintainer-email: Pablo Ulloa Santín <pablo.ulloa.santin@udc.es>
License: MIT
License-File: AUTHORS.md
License-File: LICENSE
Keywords: data-science,data-validation,dataframe,etl,frontend-integration,json-schema,machine-learning,pandas,pydantic,schema-inference,type-inference,validation
Classifier: Development Status :: 4 - Beta
Classifier: Framework :: Pydantic
Classifier: Framework :: Pytest
Classifier: Intended Audience :: Developers
Classifier: Intended Audience :: Information Technology
Classifier: Intended Audience :: Science/Research
Classifier: License :: OSI Approved :: MIT License
Classifier: Natural Language :: English
Classifier: Operating System :: MacOS
Classifier: Operating System :: Microsoft :: Windows
Classifier: Operating System :: OS Independent
Classifier: Operating System :: POSIX
Classifier: Programming Language :: Python :: 3
Classifier: Programming Language :: Python :: 3 :: Only
Classifier: Programming Language :: Python :: 3.14
Classifier: Programming Language :: Python :: Implementation :: CPython
Classifier: Topic :: Scientific/Engineering
Classifier: Topic :: Scientific/Engineering :: Information Analysis
Classifier: Topic :: Software Development :: Code Generators
Classifier: Topic :: Software Development :: Libraries :: Python Modules
Classifier: Topic :: Utilities
Classifier: Typing :: Typed
Requires-Python: <3.15,>=3.14
Requires-Dist: pandas<3.0.0,>=2.3.3
Requires-Dist: pydantic<3.0.0,>=2.12.0
